resf/__init__.py
resf/resf.py
resf-0.1.4.dist-info/LICENSE
resf-0.1.4.dist-info/METADATA
resf-0.1.4.dist-info/WHEEL
resf-0.1.4.dist-info/top_level.txt
resf-0.1.4.dist-info/RECORD
