Metadata-Version: 2.1
Name: resf
Version: 0.1.4
Summary: A simple package for displaying calculation results in a textbased table
Home-page: https://github.com/rol1510/resf
Author: Roland Strasser
Author-email: roland1510s@gmail.com
License: UNKNOWN
Platform: UNKNOWN
Classifier: Programming Language :: Python :: 3
Classifier: License :: OSI Approved :: MIT License
Classifier: Operating System :: OS Independent
Classifier: Environment :: Console
Requires-Python: >=3.6
Requires-Dist: tabulate
